MANIFEST.in
setup.cfg
setup.py
az_ipyleaflet.egg-info/PKG-INFO
az_ipyleaflet.egg-info/SOURCES.txt
az_ipyleaflet.egg-info/dependency_links.txt
az_ipyleaflet.egg-info/not-zip-safe
az_ipyleaflet.egg-info/requires.txt
az_ipyleaflet.egg-info/top_level.txt
ipyleaflet/__init__.py
ipyleaflet/_version.py
ipyleaflet/leaflet.py
ipyleaflet/static/2f19f5c5efabd77841f96226b50944c1.png
ipyleaflet/static/324b4fcaf164735c627269504b7bc28e.png
ipyleaflet/static/4296141752702dffcef4c5e327b47b39.png
ipyleaflet/static/69d89e51f62b6a582c311c35c0f778aa.svg
ipyleaflet/static/69fbc9c24b3665b801445c9bccc7017d.png
ipyleaflet/static/7cb0d2482ecadc1b80eb0abe457371b6.png
ipyleaflet/static/extension.js
ipyleaflet/static/index.js
ipyleaflet/static/index.js.map
ipyleaflet/static/marker-icon-2x.png
ipyleaflet/static/marker-icon.png
ipyleaflet/static/marker-shadow.png