Metadata-Version: 1.1
Name: az-ipyleaflet
Version: 0.4.1
Summary: A Jupyter widget for dynamic Leaflet maps
Home-page: https://github.com/ellisonbg/ipyleaflet
Author: Brian E. Granger
Author-email: ellisonbg@gmail.com
License: MIT License
Keywords: ipython,jupyter,widgets,graphics,3d
Platform: UNKNOWN
Classifier: Development Status :: 4 - Beta
Classifier: Intended Audience :: Developers
Classifier: Intended Audience :: Science/Research
Classifier: Topic :: Multimedia :: Graphics
Classifier: License :: OSI Approved :: MIT License
Classifier: Programming Language :: Python :: 2
Classifier: Programming Language :: Python :: 2.7
Classifier: Programming Language :: Python :: 3
Classifier: Programming Language :: Python :: 3.3
Classifier: Programming Language :: Python :: 3.4
Classifier: Programming Language :: Python :: 3.5
